tscalc/__init__.py
tscalc/cli.py
tscalc/core.py
tscalc-2.0.1.dist-info/METADATA
tscalc-2.0.1.dist-info/WHEEL
tscalc-2.0.1.dist-info/licenses/LICENSE
tscalc-2.0.1.dist-info/RECORD
