Metadata-Version: 2.4
Name: tscalc
Version: 2.0.1
Summary: A comprehensive assessment tool to evaluate personal attributes related to toughness, success potential, and personality type.
Project-URL: Homepage, https://github.com/CraigMLdsouza/tscalc
Project-URL: Issues, https://github.com/CraigMLdsouza/tscalc/issues
Author-email: Craig Michael Dsouza <dsouzacraigmichael@gmail.com>
License-Expression: MIT
License-File: LICENSE
Classifier: License :: OSI Approved :: MIT License
Classifier: Operating System :: OS Independent
Classifier: Programming Language :: Python :: 3
Requires-Python: >=3.9
Requires-Dist: colorama
Requires-Dist: numpy
Requires-Dist: reportlab
Requires-Dist: tabulate
